README.md
setup.cfg
setup.py
streamlit_router/__init__.py
streamlit_router.egg-info/PKG-INFO
streamlit_router.egg-info/SOURCES.txt
streamlit_router.egg-info/dependency_links.txt
streamlit_router.egg-info/requires.txt
streamlit_router.egg-info/top_level.txt