Metadata-Version: 2.1
Name: streamlit-router
Version: 0.1.1
Summary: werkzeug router for streamlit
Home-page: https://github.com/mapix/streamlit-router
Author: mapix
Author-email: mapix.me@gmail.com
Classifier: Intended Audience :: Developers
Classifier: Intended Audience :: Science/Research
Classifier: Programming Language :: Python :: 3
Classifier: Programming Language :: Python :: 3.6
Classifier: Programming Language :: Python :: 3.7
Classifier: Programming Language :: Python :: 3.8
Classifier: Programming Language :: Python :: 3.9
Classifier: Programming Language :: Python :: 3.10
Classifier: License :: OSI Approved
Classifier: Topic :: Scientific/Engineering
